rubmix/__init__.py
rubmix/builders.py
rubmix/converters.py
rubmix-1.0.1.dist-info/METADATA
rubmix-1.0.1.dist-info/WHEEL
rubmix-1.0.1.dist-info/top_level.txt
rubmix-1.0.1.dist-info/RECORD
