Metadata-Version: 2.4
Name: rubmix
Version: 1.0.1
Summary: Advanced Rubika Keypad Builder for rubpy using rubka logic.
Author: Erfan
Classifier: Programming Language :: Python :: 3
Classifier: License :: OSI Approved :: MIT License
Classifier: Operating System :: OS Independent
Requires-Python: >=3.8
Requires-Dist: rubpy
Requires-Dist: rubka
Dynamic: author
Dynamic: classifier
Dynamic: description
Dynamic: description-content-type
Dynamic: requires-dist
Dynamic: requires-python
Dynamic: summary
